Metadata-Version: 2.1
Name: pytube-robermar23
Version: 15.0.2
Summary: Python 3 library for downloading YouTube Videos.
Home-page: https://github.com/pytube/pytube
Author: Robert Evans
Author-email: robermar2@gmail.com
License: The Unlicense (Unlicense)
Project-URL: Bug Reports, https://github.com/pytube/pytube/issues
Project-URL: Read the Docs, https://pytube.io
Keywords: youtube,download,video,stream
Platform: UNKNOWN
Classifier: Development Status :: 5 - Production/Stable
Classifier: Environment :: Console
Classifier: Intended Audience :: Developers
Classifier: License :: OSI Approved :: The Unlicense (Unlicense)
Classifier: Natural Language :: English
Classifier: Operating System :: OS Independent
Classifier: Programming Language :: Python :: 3.7
Classifier: Programming Language :: Python :: 3.8
Classifier: Programming Language :: Python :: 3.9
Classifier: Programming Language :: Python :: 3.10
Classifier: Programming Language :: Python :: 3.11
Classifier: Programming Language :: Python
Classifier: Topic :: Internet
Classifier: Topic :: Multimedia :: Video
Classifier: Topic :: Software Development :: Libraries :: Python Modules
Classifier: Topic :: Terminals
Classifier: Topic :: Utilities
Requires-Python: >=3.7
License-File: LICENSE
